albero/init.py
albero/main.py
albero_viz-0.1.1.dist-info/licenses/LICENSE
albero_viz-0.1.1.dist-info/METADATA
albero_viz-0.1.1.dist-info/WHEEL
albero_viz-0.1.1.dist-info/entry_points.txt
albero_viz-0.1.1.dist-info/top_level.txt
albero_viz-0.1.1.dist-info/RECORD
